imaplib2-2.45.0.dist-info/metadata.json
imaplib2-2.45.0.dist-info/WHEEL
imaplib2-2.45.0.dist-info/top_level.txt
imaplib2-2.45.0.dist-info/METADATA
imaplib2-2.45.0.dist-info/DESCRIPTION.rst
imaplib2-2.45.0.dist-info/RECORD
imaplib2/__init__.py
imaplib2/imaplib2.py
